translationese_analyzer/__init__.py
translationese_analyzer/start_analysis.py
translationese_analyzer/tools/__init__.py
translationese_analyzer/tools/work_with_db.py
translationese_analyzer/tools/core/__init__.py
translationese_analyzer/tools/core/constants.py
translationese_analyzer/tools/core/custom_punkt_tokenizer.py
translationese_analyzer/tools/core/lemmatizators.py
translationese_analyzer/tools/core/links_removal.py
translationese_analyzer/tools/core/preprocess_text.py
translationese_analyzer/tools/core/stop_words_extraction_removal.py
translationese_analyzer/tools/core/text_preparation.py
translationese_analyzer/tools/core/tokens_counter.py
translationese_analyzer/tools/core/utils.py
translationese_analyzer/tools/core/validators.py
translationese_analyzer/tools/core/data/__init__.py
translationese_analyzer/tools/core/data/abbreviations.py
translationese_analyzer/tools/core/data/conjunctions.py
translationese_analyzer/tools/core/data/discource_markers.py
translationese_analyzer/tools/core/data/lang_word_frequencies.py
translationese_analyzer/tools/core/data/particles.py
translationese_analyzer/tools/core/data/prepositions.py
translationese_analyzer/tools/core/data/pronouns.py
translationese_analyzer/tools/explicitation/__init__.py
translationese_analyzer/tools/explicitation/explicit_naming.py
translationese_analyzer/tools/explicitation/mean_multiple_naming.py
translationese_analyzer/tools/explicitation/named_entities_extraction.py
translationese_analyzer/tools/explicitation/sci_dm_analysis.py
translationese_analyzer/tools/explicitation/single_naming.py
translationese_analyzer/tools/interference/__init__.py
translationese_analyzer/tools/interference/contextual_func_words.py
translationese_analyzer/tools/interference/n_grams_analyzer.py
translationese_analyzer/tools/interference/positional_token_freq.py
translationese_analyzer/tools/interference/positional_tokens_contexts_by_sent.py
translationese_analyzer/tools/miscellaneous/__init__.py
translationese_analyzer-0.0.0.dist-info/METADATA
translationese_analyzer-0.0.0.dist-info/WHEEL
translationese_analyzer-0.0.0.dist-info/entry_points.txt
translationese_analyzer-0.0.0.dist-info/top_level.txt
translationese_analyzer-0.0.0.dist-info/RECORD
