Metadata-Version: 2.2
Name: translationese_analyzer
Version: 0.0.0
Summary: Scientific paper translationese analyzer.
Home-page: https://github.com/serovaolesya/sci_papers_translationese
Author: Olesya Serova
Author-email: serovaolesyau@gmail.com
Classifier: Programming Language :: Python :: 3.9
Classifier: Programming Language :: Python :: 3.10
Classifier: Programming Language :: Python :: 3.11
Classifier: License :: OSI Approved :: MIT License
Classifier: Operating System :: OS Independent
Classifier: Development Status :: 5 - Production/Stable
Requires-Python: >=3.9
Requires-Dist: colorama==0.4.6
Requires-Dist: natasha==1.6.0
Requires-Dist: navec==0.10.0
Requires-Dist: nltk==3.9.1
Requires-Dist: prettytable==3.11.0
Requires-Dist: pymorphy2==0.9.1
Requires-Dist: pymorphy2-dicts-ru==2.4.417127.4579844
Requires-Dist: regex==2024.9.11
Requires-Dist: rich==13.8.1
Requires-Dist: slovnet==0.6.0
Dynamic: author
Dynamic: author-email
Dynamic: classifier
Dynamic: description
Dynamic: description-content-type
Dynamic: home-page
Dynamic: requires-dist
Dynamic: requires-python
Dynamic: summary
